laozi/__init__.py
laozi/asynclog.py
laozi-1.1.11.dist-info/LICENSE
laozi-1.1.11.dist-info/WHEEL
laozi-1.1.11.dist-info/METADATA
laozi-1.1.11.dist-info/RECORD
