Metadata-Version: 2.1
Name: laozi
Version: 1.1.11
Summary: Serialization library outputting a human-readable format
License: GPL3
Author: David Francos Cuartero
Author-email: me@davidfrancos.net
Requires-Python: >=3.10,<4.0
Classifier: License :: Other/Proprietary License
Classifier: Programming Language :: Python :: 3
Classifier: Programming Language :: Python :: 3.10
Requires-Dist: loguru
